datasette_ui_extras/__init__.py
datasette_ui_extras/column_stats.py
datasette_ui_extras/column_stats_schema.py
datasette_ui_extras/dux_command.py
datasette_ui_extras/edit_controls.py
datasette_ui_extras/edit_row_pages.py
datasette_ui_extras/facet_patches.py
datasette_ui_extras/facets.py
datasette_ui_extras/filters.py
datasette_ui_extras/hookspecs.py
datasette_ui_extras/new_facets.py
datasette_ui_extras/omnisearch.py
datasette_ui_extras/plugin.py
datasette_ui_extras/schema_utils.py
datasette_ui_extras/undux_command.py
datasette_ui_extras/utils.py
datasette_ui_extras/view_row_pages.py
datasette_ui_extras/yolo_command.py
datasette_ui_extras/static/app.css
datasette_ui_extras/static/compact-cogs.css
datasette_ui_extras/static/focus-search-box.js
datasette_ui_extras/static/hide-export.css
datasette_ui_extras/static/hide-filters.css
datasette_ui_extras/static/hide-filters.js
datasette_ui_extras/static/hide-table-definition.css
datasette_ui_extras/static/layout-row-page.css
datasette_ui_extras/static/layout-row-page.js
datasette_ui_extras/static/lazy-facets.css
datasette_ui_extras/static/lazy-facets.js
datasette_ui_extras/static/mobile-column-menu.css
datasette_ui_extras/static/mobile-column-menu.js
datasette_ui_extras/static/omnisearch.css
datasette_ui_extras/static/omnisearch.js
datasette_ui_extras/static/sticky-table-headers.css
datasette_ui_extras/static/sticky-table-headers.js
datasette_ui_extras/static/edit-row/CheckboxControl.js
datasette_ui_extras/static/edit-row/DateControl.js
datasette_ui_extras/static/edit-row/DropdownControl.js
datasette_ui_extras/static/edit-row/ForeignKeyControl.js
datasette_ui_extras/static/edit-row/JSONTagsControl.js
datasette_ui_extras/static/edit-row/NumberControl.js
datasette_ui_extras/static/edit-row/StringAutocompleteControl.js
datasette_ui_extras/static/edit-row/StringControl.js
datasette_ui_extras/static/edit-row/TextareaControl.js
datasette_ui_extras/static/edit-row/edit-row.css
datasette_ui_extras/static/edit-row/edit-row.js
datasette_ui_extras-0.31.6.dist-info/LICENSE
datasette_ui_extras-0.31.6.dist-info/METADATA
datasette_ui_extras-0.31.6.dist-info/WHEEL
datasette_ui_extras-0.31.6.dist-info/entry_points.txt
datasette_ui_extras-0.31.6.dist-info/top_level.txt
datasette_ui_extras-0.31.6.dist-info/RECORD
