Metadata-Version: 2.1
Name: datasette-ui-extras
Version: 0.31.6
Summary: Adds UI enhancements to Datasette
Home-page: https://github.com/cldellow/datasette-ui-extras
Author: Colin Dellow
License: Apache License, Version 2.0
Project-URL: Issues, https://github.com/cldellow/datasette-ui-extras/issues
Project-URL: CI, https://github.com/cldellow/datasette-ui-extras/actions
Project-URL: Changelog, https://github.com/cldellow/datasette-ui-extras/releases
Classifier: Framework :: Datasette
Classifier: License :: OSI Approved :: Apache Software License
Requires-Python: >=3.7
License-File: LICENSE
Requires-Dist: datasette (>=1.0a0)
Requires-Dist: sqlglot
Requires-Dist: sqlite-sqlean (==0.1)
Requires-Dist: datasette-mutable-downloads
Provides-Extra: test
Requires-Dist: pytest ; extra == 'test'
Requires-Dist: pytest-asyncio ; extra == 'test'
Requires-Dist: pytest-watch ; extra == 'test'
Requires-Dist: sqlite-utils ; extra == 'test'
Requires-Dist: coverage ; extra == 'test'
Requires-Dist: pytest-cov ; extra == 'test'
